xdialog/__init__.py
xdialog/constants.py
xdialog/mac_dialogs.py
xdialog/test.py
xdialog/tk_dialogs.py
xdialog/windows_dialogs.py
xdialog/windows_structs.py
xdialog/zenity_dialogs.py
xdialog-1.1.1.1.dist-info/LICENSE
xdialog-1.1.1.1.dist-info/METADATA
xdialog-1.1.1.1.dist-info/WHEEL
xdialog-1.1.1.1.dist-info/top_level.txt
xdialog-1.1.1.1.dist-info/RECORD
