Metadata-Version: 2.1
Name: xdialog
Version: 1.1.1.1
Summary: A cross-platform python wrapper for native dialogs.
Home-page: https://github.com/xMGZx/xdialog
Author: mathgeniuszach
Author-email: huntingmanzach@gmail.com
License: MIT License
Classifier: Programming Language :: Python :: 3
License-File: LICENSE
